demandify/__init__.py
demandify/__main__.py
demandify/app.py
demandify/cli.py
demandify/config.py
demandify/pipeline.py
demandify/cache/__init__.py
demandify/cache/keys.py
demandify/cache/manager.py
demandify/calibration/__init__.py
demandify/calibration/objective.py
demandify/calibration/optimizer.py
demandify/calibration/worker.py
demandify/export/__init__.py
demandify/export/custom_formats.py
demandify/export/exporter.py
demandify/export/report.py
demandify/export/visualize.py
demandify/providers/__init__.py
demandify/providers/base.py
demandify/providers/osm.py
demandify/providers/tomtom.py
demandify/static/banner.png
demandify/static/icon.png
demandify/static/css/style.css
demandify/static/js/app.js
demandify/sumo/__init__.py
demandify/sumo/demand.py
demandify/sumo/matching.py
demandify/sumo/network.py
demandify/sumo/simulation.py
demandify/templates/api_key_section.html
demandify/templates/index.html
demandify/utils/__init__.py
demandify/utils/geometry.py
demandify/utils/logger.py
demandify/utils/logging.py
demandify/utils/validation.py
demandify/utils/visualization.py
demandify/web/__init__.py
demandify/web/routes.py
demandify-0.0.1.dist-info/licenses/LICENSE
demandify-0.0.1.dist-info/METADATA
demandify-0.0.1.dist-info/WHEEL
demandify-0.0.1.dist-info/entry_points.txt
demandify-0.0.1.dist-info/top_level.txt
demandify-0.0.1.dist-info/RECORD
